a_pandas_ex_text_compare/LICENSE
a_pandas_ex_text_compare/README.MD
a_pandas_ex_text_compare/__init__.py
a_pandas_ex_text_compare/requirements.txt
a_pandas_ex_text_compare/thirdparty.json
a_pandas_ex_text_compare-0.11.dist-info/LICENSE.rst
a_pandas_ex_text_compare-0.11.dist-info/METADATA
a_pandas_ex_text_compare-0.11.dist-info/WHEEL
a_pandas_ex_text_compare-0.11.dist-info/top_level.txt
a_pandas_ex_text_compare-0.11.dist-info/RECORD
