Metadata-Version: 2.1
Name: a-pandas-ex-text-compare
Version: 0.11
Summary: Compares 2 texts with each other, and returns a Pandas DataFrame
Home-page: https://github.com/hansalemaos/a_pandas_ex_text_compare
Author: Johannes Fischer
Author-email: aulasparticularesdealemaosp@gmail.com
License: MIT
Keywords: string,text,pandas,DataFrame,read,difflib,fuzz,fuzzy
Classifier: Development Status :: 4 - Beta
Classifier: Programming Language :: Python :: 3 :: Only
Classifier: Programming Language :: Python :: 3.10
Classifier: Topic :: Software Development :: Libraries :: Python Modules
Classifier: Topic :: Utilities
License-File: LICENSE.rst
Requires-Dist: a-pandas-ex-bs4df-lite
Requires-Dist: flatten-everything
Requires-Dist: pandas
Requires-Dist: regex
